Classfile jar:file:///D:/IDEA/project/ArcartXSuite/libs/Chemdah-1.1.33-FREE.jar!/ink/ptms/chemdah/core/database/QuestTable$SQL$questData$1.class
  Last modified 2026年6月4日; size 3565 bytes
  SHA-256 checksum 9aea96d0ff2663bb5471ebd7cdbbb851ca515fcdee702bcdcd7fbf57203566be
  Compiled from "QuestTable.kt"
final class ink.ptms.chemdah.core.database.QuestTable$SQL$questData$1 extends kotlin1822.jvm.internal.Lambda implements kotlin1822.jvm.functions.Function1<ink.ptms.chemdah.taboolib.module.database.Table<ink.ptms.chemdah.taboolib.module.database.Host<ink.ptms.chemdah.taboolib.module.database.SQL>, ink.ptms.chemdah.taboolib.module.database.SQL>, kotlin1822.Unit>
  minor version: 0
  major version: 52
  flags: (0x0030) ACC_FINAL, ACC_SUPER
  this_class: #2                          // ink/ptms/chemdah/core/database/QuestTable$SQL$questData$1
  super_class: #5                         // kotlin1822/jvm/internal/Lambda
  interfaces: 1, fields: 1, methods: 4, attributes: 5
Constant pool:
    #1 = Utf8               ink/ptms/chemdah/core/database/QuestTable$SQL$questData$1
    #2 = Class              #1            // ink/ptms/chemdah/core/database/QuestTable$SQL$questData$1
    #3 = Utf8               Lkotlin1822/jvm/internal/Lambda;Lkotlin1822/jvm/functions/Function1<Link/ptms/chemdah/taboolib/module/database/Table<Link/ptms/chemdah/taboolib/module/database/Host<Link/ptms/chemdah/taboolib/module/database/SQL;>;Link/ptms/chemdah/taboolib/module/database/SQL;>;Lkotlin1822/Unit;>;
    #4 = Utf8               kotlin1822/jvm/internal/Lambda
    #5 = Class              #4            // kotlin1822/jvm/internal/Lambda
    #6 = Utf8               kotlin1822/jvm/functions/Function1
    #7 = Class              #6            // kotlin1822/jvm/functions/Function1
    #8 = Utf8               QuestTable.kt
    #9 = Utf8               ink/ptms/chemdah/core/database/QuestTable$SQL
   #10 = Class              #9            // ink/ptms/chemdah/core/database/QuestTable$SQL
   #11 = Utf8               <init>
   #12 = Utf8               (Link/ptms/chemdah/taboolib/module/database/HostSQL;Ljava/lang/String;Ljava/lang/String;)V
   #13 = NameAndType        #11:#12       // "<init>":(Link/ptms/chemdah/taboolib/module/database/HostSQL;Ljava/lang/String;Ljava/lang/String;)V
   #14 = Utf8               Lkotlin/Metadata;
   #15 = Utf8               mv
   #16 = Integer            1
   #17 = Integer            8
   #18 = Integer            0
   #19 = Utf8               k
   #20 = Integer            3
   #21 = Utf8               xi
   #22 = Integer            48
   #23 = Utf8               d1
   #24 = Utf8               \u0000\u001a\n\u0000\n\u0002\u0010\u0002\n\u0000\n\u0002\u0018\u0002\n\u0002\u0018\u0002\n\u0002\u0018\u0002\n\u0002\u0018\u0002\n\u0000\u0010\u0000\u001a\u00020\u0001\"\b\b\u0000\u0010\u0002*\u00020\u0003*\u0014\u0012\n\u0012\b\u0012\u0004\u0012\u00020\u00060\u0005\u0012\u0004\u0012\u00020\u00060\u0004H\n¢\u0006\u0002\b\u0007
   #25 = Utf8               d2
   #26 = Utf8               <anonymous>
   #27 = Utf8
   #28 = Utf8               T
   #29 = Utf8               Link/ptms/chemdah/taboolib/module/database/ColumnBuilder;
   #30 = Utf8               Link/ptms/chemdah/taboolib/module/database/Table;
   #31 = Utf8               Link/ptms/chemdah/taboolib/module/database/Host;
   #32 = Utf8               Link/ptms/chemdah/taboolib/module/database/SQL;
   #33 = Utf8               invoke
   #34 = Utf8               ink/ptms/chemdah/core/database/QuestTable
   #35 = Class              #34           // ink/ptms/chemdah/core/database/QuestTable
   #36 = Utf8               SQL
   #37 = Utf8               ink/ptms/chemdah/core/database/QuestTable$SQL$questData$1$1
   #38 = Class              #37           // ink/ptms/chemdah/core/database/QuestTable$SQL$questData$1$1
   #39 = Utf8               ink/ptms/chemdah/core/database/QuestTable$SQL$questData$1$2
   #40 = Class              #39           // ink/ptms/chemdah/core/database/QuestTable$SQL$questData$1$2
   #41 = Utf8               ink/ptms/chemdah/core/database/QuestTable$SQL$questData$1$3
   #42 = Class              #41           // ink/ptms/chemdah/core/database/QuestTable$SQL$questData$1$3
   #43 = Utf8               ink/ptms/chemdah/core/database/QuestTable$SQL$questData$1$4
   #44 = Class              #43           // ink/ptms/chemdah/core/database/QuestTable$SQL$questData$1$4
   #45 = Utf8               ink/ptms/chemdah/core/database/QuestTable$SQL$questData$1$5
   #46 = Class              #45           // ink/ptms/chemdah/core/database/QuestTable$SQL$questData$1$5
   #47 = Utf8               INSTANCE
   #48 = Utf8               Link/ptms/chemdah/core/database/QuestTable$SQL$questData$1;
   #49 = Utf8               ()V
   #50 = Utf8               (I)V
   #51 = NameAndType        #11:#50       // "<init>":(I)V
   #52 = Methodref          #5.#51        // kotlin1822/jvm/internal/Lambda."<init>":(I)V
   #53 = Utf8               this
   #54 = Utf8               (Link/ptms/chemdah/taboolib/module/database/Table;)V
   #55 = Utf8               (Link/ptms/chemdah/taboolib/module/database/Table<Link/ptms/chemdah/taboolib/module/database/Host<Link/ptms/chemdah/taboolib/module/database/SQL;>;Link/ptms/chemdah/taboolib/module/database/SQL;>;)V
   #56 = Utf8               Lorg/jetbrains/annotations/NotNull;
   #57 = Utf8               $this$$receiver
   #58 = String             #57           // $this$$receiver
   #59 = Utf8               kotlin1822/jvm/internal/Intrinsics
   #60 = Class              #59           // kotlin1822/jvm/internal/Intrinsics
   #61 = Utf8               checkNotNullParameter
   #62 = Utf8               (Ljava/lang/Object;Ljava/lang/String;)V
   #63 = NameAndType        #61:#62       // checkNotNullParameter:(Ljava/lang/Object;Ljava/lang/String;)V
   #64 = Methodref          #60.#63       // kotlin1822/jvm/internal/Intrinsics.checkNotNullParameter:(Ljava/lang/Object;Ljava/lang/String;)V
   #65 = Utf8               Link/ptms/chemdah/core/database/QuestTable$SQL$questData$1$1;
   #66 = NameAndType        #47:#65       // INSTANCE:Link/ptms/chemdah/core/database/QuestTable$SQL$questData$1$1;
   #67 = Fieldref           #38.#66       // ink/ptms/chemdah/core/database/QuestTable$SQL$questData$1$1.INSTANCE:Link/ptms/chemdah/core/database/QuestTable$SQL$questData$1$1;
   #68 = Utf8               ink/ptms/chemdah/taboolib/module/database/Table
   #69 = Class              #68           // ink/ptms/chemdah/taboolib/module/database/Table
   #70 = Utf8               add$default
   #71 = Utf8               (Link/ptms/chemdah/taboolib/module/database/Table;Ljava/lang/String;Lkotlin1822/jvm/functions/Function1;ILjava/lang/Object;)Link/ptms/chemdah/taboolib/module/database/Table;
   #72 = NameAndType        #70:#71       // add$default:(Link/ptms/chemdah/taboolib/module/database/Table;Ljava/lang/String;Lkotlin1822/jvm/functions/Function1;ILjava/lang/Object;)Link/ptms/chemdah/taboolib/module/database/Table;
   #73 = Methodref          #69.#72       // ink/ptms/chemdah/taboolib/module/database/Table.add$default:(Link/ptms/chemdah/taboolib/module/database/Table;Ljava/lang/String;Lkotlin1822/jvm/functions/Function1;ILjava/lang/Object;)Link/ptms/chemdah/taboolib/module/database/Table;
   #74 = Utf8               quest
   #75 = String             #74           // quest
   #76 = Utf8               Link/ptms/chemdah/core/database/QuestTable$SQL$questData$1$2;
   #77 = NameAndType        #47:#76       // INSTANCE:Link/ptms/chemdah/core/database/QuestTable$SQL$questData$1$2;
   #78 = Fieldref           #40.#77       // ink/ptms/chemdah/core/database/QuestTable$SQL$questData$1$2.INSTANCE:Link/ptms/chemdah/core/database/QuestTable$SQL$questData$1$2;
   #79 = Utf8               add
   #80 = Utf8               (Ljava/lang/String;Lkotlin1822/jvm/functions/Function1;)Link/ptms/chemdah/taboolib/module/database/Table;
   #81 = NameAndType        #79:#80       // add:(Ljava/lang/String;Lkotlin1822/jvm/functions/Function1;)Link/ptms/chemdah/taboolib/module/database/Table;
   #82 = Methodref          #69.#81       // ink/ptms/chemdah/taboolib/module/database/Table.add:(Ljava/lang/String;Lkotlin1822/jvm/functions/Function1;)Link/ptms/chemdah/taboolib/module/database/Table;
   #83 = Utf8               key
   #84 = String             #83           // key
   #85 = Utf8               Link/ptms/chemdah/core/database/QuestTable$SQL$questData$1$3;
   #86 = NameAndType        #47:#85       // INSTANCE:Link/ptms/chemdah/core/database/QuestTable$SQL$questData$1$3;
   #87 = Fieldref           #42.#86       // ink/ptms/chemdah/core/database/QuestTable$SQL$questData$1$3.INSTANCE:Link/ptms/chemdah/core/database/QuestTable$SQL$questData$1$3;
   #88 = Utf8               value
   #89 = String             #88           // value
   #90 = Utf8               Link/ptms/chemdah/core/database/QuestTable$SQL$questData$1$4;
   #91 = NameAndType        #47:#90       // INSTANCE:Link/ptms/chemdah/core/database/QuestTable$SQL$questData$1$4;
   #92 = Fieldref           #44.#91       // ink/ptms/chemdah/core/database/QuestTable$SQL$questData$1$4.INSTANCE:Link/ptms/chemdah/core/database/QuestTable$SQL$questData$1$4;
   #93 = Utf8               mode
   #94 = String             #93           // mode
   #95 = Utf8               Link/ptms/chemdah/core/database/QuestTable$SQL$questData$1$5;
   #96 = NameAndType        #47:#95       // INSTANCE:Link/ptms/chemdah/core/database/QuestTable$SQL$questData$1$5;
   #97 = Fieldref           #46.#96       // ink/ptms/chemdah/core/database/QuestTable$SQL$questData$1$5.INSTANCE:Link/ptms/chemdah/core/database/QuestTable$SQL$questData$1$5;
   #98 = Utf8               (Ljava/lang/Object;)Ljava/lang/Object;
   #99 = NameAndType        #33:#54       // invoke:(Link/ptms/chemdah/taboolib/module/database/Table;)V
  #100 = Methodref          #2.#99        // ink/ptms/chemdah/core/database/QuestTable$SQL$questData$1.invoke:(Link/ptms/chemdah/taboolib/module/database/Table;)V
  #101 = Utf8               kotlin1822/Unit
  #102 = Class              #101          // kotlin1822/Unit
  #103 = Utf8               Lkotlin1822/Unit;
  #104 = NameAndType        #47:#103      // INSTANCE:Lkotlin1822/Unit;
  #105 = Fieldref           #102.#104     // kotlin1822/Unit.INSTANCE:Lkotlin1822/Unit;
  #106 = Utf8               p1
  #107 = Utf8               Ljava/lang/Object;
  #108 = Utf8               <clinit>
  #109 = NameAndType        #11:#49       // "<init>":()V
  #110 = Methodref          #2.#109       // ink/ptms/chemdah/core/database/QuestTable$SQL$questData$1."<init>":()V
  #111 = NameAndType        #47:#48       // INSTANCE:Link/ptms/chemdah/core/database/QuestTable$SQL$questData$1;
  #112 = Fieldref           #2.#111       // ink/ptms/chemdah/core/database/QuestTable$SQL$questData$1.INSTANCE:Link/ptms/chemdah/core/database/QuestTable$SQL$questData$1;
  #113 = Utf8               Code
  #114 = Utf8               LocalVariableTable
  #115 = Utf8               LineNumberTable
  #116 = Utf8               Signature
  #117 = Utf8               RuntimeInvisibleParameterAnnotations
  #118 = Utf8               InnerClasses
  #119 = Utf8               EnclosingMethod
  #120 = Utf8               SourceFile
  #121 = Utf8               RuntimeVisibleAnnotations
{
  public static final ink.ptms.chemdah.core.database.QuestTable$SQL$questData$1 INSTANCE;
    descriptor: Link/ptms/chemdah/core/database/QuestTable$SQL$questData$1;
    flags: (0x0019) ACC_PUBLIC, ACC_STATIC, ACC_FINAL

  ink.ptms.chemdah.core.database.QuestTable$SQL$questData$1();
    descriptor: ()V
    flags: (0x0000)
    Code:
      stack=2, locals=1, args_size=1
         0: aload_0
         1: iconst_1
         2: invokespecial #52                 // Method kotlin1822/jvm/internal/Lambda."<init>":(I)V
         5: return
      LocalVariableTable:
        Start  Length  Slot  Name   Signature
            0       6     0  this   Link/ptms/chemdah/core/database/QuestTable$SQL$questData$1;

  public final void invoke(ink.ptms.chemdah.taboolib.module.database.Table<ink.ptms.chemdah.taboolib.module.database.Host<ink.ptms.chemdah.taboolib.module.database.SQL>, ink.ptms.chemdah.taboolib.module.database.SQL>);
    descriptor: (Link/ptms/chemdah/taboolib/module/database/Table;)V
    flags: (0x0011) ACC_PUBLIC, ACC_FINAL
    Code:
      stack=5, locals=2, args_size=2
         0: aload_1
         1: ldc           #58                 // String $this$$receiver
         3: invokestatic  #64                 // Method kotlin1822/jvm/internal/Intrinsics.checkNotNullParameter:(Ljava/lang/Object;Ljava/lang/String;)V
         6: aload_1
         7: aconst_null
         8: getstatic     #67                 // Field ink/ptms/chemdah/core/database/QuestTable$SQL$questData$1$1.INSTANCE:Link/ptms/chemdah/core/database/QuestTable$SQL$questData$1$1;
        11: checkcast     #7                  // class kotlin1822/jvm/functions/Function1
        14: iconst_1
        15: aconst_null
        16: invokestatic  #73                 // Method ink/ptms/chemdah/taboolib/module/database/Table.add$default:(Link/ptms/chemdah/taboolib/module/database/Table;Ljava/lang/String;Lkotlin1822/jvm/functions/Function1;ILjava/lang/Object;)Link/ptms/chemdah/taboolib/module/database/Table;
        19: pop
        20: aload_1
        21: ldc           #75                 // String quest
        23: getstatic     #78                 // Field ink/ptms/chemdah/core/database/QuestTable$SQL$questData$1$2.INSTANCE:Link/ptms/chemdah/core/database/QuestTable$SQL$questData$1$2;
        26: checkcast     #7                  // class kotlin1822/jvm/functions/Function1
        29: invokevirtual #82                 // Method ink/ptms/chemdah/taboolib/module/database/Table.add:(Ljava/lang/String;Lkotlin1822/jvm/functions/Function1;)Link/ptms/chemdah/taboolib/module/database/Table;
        32: pop
        33: aload_1
        34: ldc           #84                 // String key
        36: getstatic     #87                 // Field ink/ptms/chemdah/core/database/QuestTable$SQL$questData$1$3.INSTANCE:Link/ptms/chemdah/core/database/QuestTable$SQL$questData$1$3;
        39: checkcast     #7                  // class kotlin1822/jvm/functions/Function1
        42: invokevirtual #82                 // Method ink/ptms/chemdah/taboolib/module/database/Table.add:(Ljava/lang/String;Lkotlin1822/jvm/functions/Function1;)Link/ptms/chemdah/taboolib/module/database/Table;
        45: pop
        46: aload_1
        47: ldc           #89                 // String value
        49: getstatic     #92                 // Field ink/ptms/chemdah/core/database/QuestTable$SQL$questData$1$4.INSTANCE:Link/ptms/chemdah/core/database/QuestTable$SQL$questData$1$4;
        52: checkcast     #7                  // class kotlin1822/jvm/functions/Function1
        55: invokevirtual #82                 // Method ink/ptms/chemdah/taboolib/module/database/Table.add:(Ljava/lang/String;Lkotlin1822/jvm/functions/Function1;)Link/ptms/chemdah/taboolib/module/database/Table;
        58: pop
        59: aload_1
        60: ldc           #94                 // String mode
        62: getstatic     #97                 // Field ink/ptms/chemdah/core/database/QuestTable$SQL$questData$1$5.INSTANCE:Link/ptms/chemdah/core/database/QuestTable$SQL$questData$1$5;
        65: checkcast     #7                  // class kotlin1822/jvm/functions/Function1
        68: invokevirtual #82                 // Method ink/ptms/chemdah/taboolib/module/database/Table.add:(Ljava/lang/String;Lkotlin1822/jvm/functions/Function1;)Link/ptms/chemdah/taboolib/module/database/Table;
        71: pop
        72: return
      LineNumberTable:
        line 42: 6
        line 43: 20
        line 46: 33
        line 49: 46
        line 52: 59
        line 55: 72
      LocalVariableTable:
        Start  Length  Slot  Name   Signature
            0      73     0  this   Link/ptms/chemdah/core/database/QuestTable$SQL$questData$1;
            0      73     1 $this$$receiver   Link/ptms/chemdah/taboolib/module/database/Table;
    Signature: #55                          // (Link/ptms/chemdah/taboolib/module/database/Table<Link/ptms/chemdah/taboolib/module/database/Host<Link/ptms/chemdah/taboolib/module/database/SQL;>;Link/ptms/chemdah/taboolib/module/database/SQL;>;)V
    RuntimeInvisibleParameterAnnotations:
      parameter 0:
        0: #56()
          org.jetbrains.annotations.NotNull

  public java.lang.Object invoke(java.lang.Object);
    descriptor: (Ljava/lang/Object;)Ljava/lang/Object;
    flags: (0x1041) ACC_PUBLIC, ACC_BRIDGE, ACC_SYNTHETIC
    Code:
      stack=2, locals=2, args_size=2
         0: aload_0
         1: aload_1
         2: checkcast     #69                 // class ink/ptms/chemdah/taboolib/module/database/Table
         5: invokevirtual #100                // Method invoke:(Link/ptms/chemdah/taboolib/module/database/Table;)V
         8: getstatic     #105                // Field kotlin1822/Unit.INSTANCE:Lkotlin1822/Unit;
        11: areturn
      LineNumberTable:
        line 41: 0
      LocalVariableTable:
        Start  Length  Slot  Name   Signature
            0      12     0  this   Link/ptms/chemdah/core/database/QuestTable$SQL$questData$1;
            0      12     1    p1   Ljava/lang/Object;

  static {};
    descriptor: ()V
    flags: (0x0008) ACC_STATIC
    Code:
      stack=2, locals=0, args_size=0
         0: new           #2                  // class ink/ptms/chemdah/core/database/QuestTable$SQL$questData$1
         3: dup
         4: invokespecial #110                // Method "<init>":()V
         7: putstatic     #112                // Field INSTANCE:Link/ptms/chemdah/core/database/QuestTable$SQL$questData$1;
        10: return
}
InnerClasses:
  public static final #36= #10 of #35;    // SQL=class ink/ptms/chemdah/core/database/QuestTable$SQL of class ink/ptms/chemdah/core/database/QuestTable
  static final #2;                        // class ink/ptms/chemdah/core/database/QuestTable$SQL$questData$1
  static final #38;                       // class ink/ptms/chemdah/core/database/QuestTable$SQL$questData$1$1
  static final #40;                       // class ink/ptms/chemdah/core/database/QuestTable$SQL$questData$1$2
  static final #42;                       // class ink/ptms/chemdah/core/database/QuestTable$SQL$questData$1$3
  static final #44;                       // class ink/ptms/chemdah/core/database/QuestTable$SQL$questData$1$4
  static final #46;                       // class ink/ptms/chemdah/core/database/QuestTable$SQL$questData$1$5
EnclosingMethod: #10.#13                // ink.ptms.chemdah.core.database.QuestTable$SQL.<init>
Signature: #3                           // Lkotlin1822/jvm/internal/Lambda;Lkotlin1822/jvm/functions/Function1<Link/ptms/chemdah/taboolib/module/database/Table<Link/ptms/chemdah/taboolib/module/database/Host<Link/ptms/chemdah/taboolib/module/database/SQL;>;Link/ptms/chemdah/taboolib/module/database/SQL;>;Lkotlin1822/Unit;>;
SourceFile: "QuestTable.kt"
RuntimeVisibleAnnotations:
  0: #14(#15=[I#16,I#17,I#18],#19=I#20,#21=I#22,#23=[s#24],#25=[s#26,s#27,s#28,s#29,s#30,s#31,s#32,s#33])
    kotlin.Metadata(
      mv=[1,8,0]
      k=3
      xi=48
      d1=["\u0000\u001a\n\u0000\n\u0002\u0010\u0002\n\u0000\n\u0002\u0018\u0002\n\u0002\u0018\u0002\n\u0002\u0018\u0002\n\u0002\u0018\u0002\n\u0000\u0010\u0000\u001a\u00020\u0001\"\b\b\u0000\u0010\u0002*\u00020\u0003*\u0014\u0012\n\u0012\b\u0012\u0004\u0012\u00020\u00060\u0005\u0012\u0004\u0012\u00020\u00060\u0004H\n¢\u0006\u0002\b\u0007"]
      d2=["<anonymous>","","T","Link/ptms/chemdah/taboolib/module/database/ColumnBuilder;","Link/ptms/chemdah/taboolib/module/database/Table;","Link/ptms/chemdah/taboolib/module/database/Host;","Link/ptms/chemdah/taboolib/module/database/SQL;","invoke"]
    )
