###### DatabaseSQL$tableUser$1
final class ink.ptms.chemdah.core.database.DatabaseSQL$tableUser$1 extends kotlin1822.jvm.internal.Lambda implements kotlin1822.jvm.functions.Function1<ink.ptms.chemdah.taboolib.module.database.Table<ink.ptms.chemdah.taboolib.module.database.Host<ink.ptms.chemdah.taboolib.module.database.SQL>, ink.ptms.chemdah.taboolib.module.database.SQL>, kotlin1822.Unit> {
  public static final ink.ptms.chemdah.core.database.DatabaseSQL$tableUser$1 INSTANCE;

  ink.ptms.chemdah.core.database.DatabaseSQL$tableUser$1();
    Code:
       0: aload_0
       1: iconst_1
       2: invokespecial #44                 // Method kotlin1822/jvm/internal/Lambda."<init>":(I)V
       5: return

  public final void invoke(ink.ptms.chemdah.taboolib.module.database.Table<ink.ptms.chemdah.taboolib.module.database.Host<ink.ptms.chemdah.taboolib.module.database.SQL>, ink.ptms.chemdah.taboolib.module.database.SQL>);
    Code:
       0: aload_1
       1: ldc           #50                 // String $this$$receiver
       3: invokestatic  #56                 // Method kotlin1822/jvm/internal/Intrinsics.checkNotNullParameter:(Ljava/lang/Object;Ljava/lang/String;)V
       6: aload_1
       7: aconst_null
       8: getstatic     #59                 // Field ink/ptms/chemdah/core/database/DatabaseSQL$tableUser$1$1.INSTANCE:Link/ptms/chemdah/core/database/DatabaseSQL$tableUser$1$1;
      11: checkcast     #7                  // class kotlin1822/jvm/functions/Function1
      14: iconst_1
      15: aconst_null
      16: invokestatic  #65                 // Method ink/ptms/chemdah/taboolib/module/database/Table.add$default:(Link/ptms/chemdah/taboolib/module/database/Table;Ljava/lang/String;Lkotlin1822/jvm/functions/Function1;ILjava/lang/Object;)Link/ptms/chemdah/taboolib/module/database/Table;
      19: pop
      20: aload_1
      21: ldc           #67                 // String name
      23: getstatic     #70                 // Field ink/ptms/chemdah/core/database/DatabaseSQL$tableUser$1$2.INSTANCE:Link/ptms/chemdah/core/database/DatabaseSQL$tableUser$1$2;
      26: checkcast     #7                  // class kotlin1822/jvm/functions/Function1
      29: invokevirtual #74                 // Method ink/ptms/chemdah/taboolib/module/database/Table.add:(Ljava/lang/String;Lkotlin1822/jvm/functions/Function1;)Link/ptms/chemdah/taboolib/module/database/Table;
      32: pop
      33: aload_1
      34: ldc           #76                 // String uuid
      36: getstatic     #79                 // Field ink/ptms/chemdah/core/database/DatabaseSQL$tableUser$1$3.INSTANCE:Link/ptms/chemdah/core/database/DatabaseSQL$tableUser$1$3;
      39: checkcast     #7                  // class kotlin1822/jvm/functions/Function1
      42: invokevirtual #74                 // Method ink/ptms/chemdah/taboolib/module/database/Table.add:(Ljava/lang/String;Lkotlin1822/jvm/functions/Function1;)Link/ptms/chemdah/taboolib/module/database/Table;
      45: pop
      46: aload_1
      47: ldc           #81                 // String time
      49: getstatic     #84                 // Field ink/ptms/chemdah/core/database/DatabaseSQL$tableUser$1$4.INSTANCE:Link/ptms/chemdah/core/database/DatabaseSQL$tableUser$1$4;
      52: checkcast     #7                  // class kotlin1822/jvm/functions/Function1
      55: invokevirtual #74                 // Method ink/ptms/chemdah/taboolib/module/database/Table.add:(Ljava/lang/String;Lkotlin1822/jvm/functions/Function1;)Link/ptms/chemdah/taboolib/module/database/Table;
      58: pop
      59: return

  public java.lang.Object invoke(java.lang.Object);
    Code:
       0: aload_0
       1: aload_1
       2: checkcast     #61                 // class ink/ptms/chemdah/taboolib/module/database/Table
       5: invokevirtual #87                 // Method invoke:(Link/ptms/chemdah/taboolib/module/database/Table;)V
       8: getstatic     #92                 // Field kotlin1822/Unit.INSTANCE:Lkotlin1822/Unit;
      11: areturn

  static {};
    Code:
       0: new           #2                  // class ink/ptms/chemdah/core/database/DatabaseSQL$tableUser$1
       3: dup
       4: invokespecial #96                 // Method "<init>":()V
       7: putstatic     #98                 // Field INSTANCE:Link/ptms/chemdah/core/database/DatabaseSQL$tableUser$1;
      10: return
###### DatabaseSQL$tableUser$1$1
final class ink.ptms.chemdah.core.database.DatabaseSQL$tableUser$1$1 extends kotlin1822.jvm.internal.Lambda implements kotlin1822.jvm.functions.Function1<ink.ptms.chemdah.taboolib.module.database.SQL, kotlin1822.Unit> {
  public static final ink.ptms.chemdah.core.database.DatabaseSQL$tableUser$1$1 INSTANCE;

  ink.ptms.chemdah.core.database.DatabaseSQL$tableUser$1$1();
    Code:
       0: aload_0
       1: iconst_1
       2: invokespecial #35                 // Method kotlin1822/jvm/internal/Lambda."<init>":(I)V
       5: return

  public final void invoke(ink.ptms.chemdah.taboolib.module.database.SQL);
    Code:
       0: aload_1
       1: ldc           #40                 // String $this$add
       3: invokestatic  #46                 // Method kotlin1822/jvm/internal/Intrinsics.checkNotNullParameter:(Ljava/lang/Object;Ljava/lang/String;)V
       6: aload_1
       7: invokevirtual #51                 // Method ink/ptms/chemdah/taboolib/module/database/SQL.id:()V
      10: return

  public java.lang.Object invoke(java.lang.Object);
    Code:
       0: aload_0
       1: aload_1
       2: checkcast     #48                 // class ink/ptms/chemdah/taboolib/module/database/SQL
       5: invokevirtual #54                 // Method invoke:(Link/ptms/chemdah/taboolib/module/database/SQL;)V
       8: getstatic     #59                 // Field kotlin1822/Unit.INSTANCE:Lkotlin1822/Unit;
      11: areturn

  static {};
    Code:
       0: new           #2                  // class ink/ptms/chemdah/core/database/DatabaseSQL$tableUser$1$1
       3: dup
       4: invokespecial #64                 // Method "<init>":()V
       7: putstatic     #66                 // Field INSTANCE:Link/ptms/chemdah/core/database/DatabaseSQL$tableUser$1$1;
      10: return
###### DatabaseSQL$tableUser$1$2
final class ink.ptms.chemdah.core.database.DatabaseSQL$tableUser$1$2 extends kotlin1822.jvm.internal.Lambda implements kotlin1822.jvm.functions.Function1<ink.ptms.chemdah.taboolib.module.database.SQL, kotlin1822.Unit> {
  public static final ink.ptms.chemdah.core.database.DatabaseSQL$tableUser$1$2 INSTANCE;

  ink.ptms.chemdah.core.database.DatabaseSQL$tableUser$1$2();
    Code:
       0: aload_0
       1: iconst_1
       2: invokespecial #37                 // Method kotlin1822/jvm/internal/Lambda."<init>":(I)V
       5: return

  public final void invoke(ink.ptms.chemdah.taboolib.module.database.SQL);
    Code:
       0: aload_1
       1: ldc           #42                 // String $this$add
       3: invokestatic  #48                 // Method kotlin1822/jvm/internal/Intrinsics.checkNotNullParameter:(Ljava/lang/Object;Ljava/lang/String;)V
       6: aload_1
       7: getstatic     #54                 // Field ink/ptms/chemdah/taboolib/module/database/ColumnTypeSQL.VARCHAR:Link/ptms/chemdah/taboolib/module/database/ColumnTypeSQL;
      10: bipush        36
      12: iconst_0
      13: getstatic     #57                 // Field ink/ptms/chemdah/core/database/DatabaseSQL$tableUser$1$2$1.INSTANCE:Link/ptms/chemdah/core/database/DatabaseSQL$tableUser$1$2$1;
      16: checkcast     #7                  // class kotlin1822/jvm/functions/Function1
      19: iconst_4
      20: aconst_null
      21: invokestatic  #63                 // Method ink/ptms/chemdah/taboolib/module/database/SQL.type$default:(Link/ptms/chemdah/taboolib/module/database/SQL;Link/ptms/chemdah/taboolib/module/database/ColumnTypeSQL;IILkotlin1822/jvm/functions/Function1;ILjava/lang/Object;)V
      24: return

  public java.lang.Object invoke(java.lang.Object);
    Code:
       0: aload_0
       1: aload_1
       2: checkcast     #59                 // class ink/ptms/chemdah/taboolib/module/database/SQL
       5: invokevirtual #66                 // Method invoke:(Link/ptms/chemdah/taboolib/module/database/SQL;)V
       8: getstatic     #71                 // Field kotlin1822/Unit.INSTANCE:Lkotlin1822/Unit;
      11: areturn

  static {};
    Code:
       0: new           #2                  // class ink/ptms/chemdah/core/database/DatabaseSQL$tableUser$1$2
       3: dup
       4: invokespecial #76                 // Method "<init>":()V
       7: putstatic     #78                 // Field INSTANCE:Link/ptms/chemdah/core/database/DatabaseSQL$tableUser$1$2;
      10: return
###### DatabaseSQL$tableUser$1$2$1
final class ink.ptms.chemdah.core.database.DatabaseSQL$tableUser$1$2$1 extends kotlin1822.jvm.internal.Lambda implements kotlin1822.jvm.functions.Function1<ink.ptms.chemdah.taboolib.module.database.ColumnSQL, kotlin1822.Unit> {
  public static final ink.ptms.chemdah.core.database.DatabaseSQL$tableUser$1$2$1 INSTANCE;

  ink.ptms.chemdah.core.database.DatabaseSQL$tableUser$1$2$1();
    Code:
       0: aload_0
       1: iconst_1
       2: invokespecial #37                 // Method kotlin1822/jvm/internal/Lambda."<init>":(I)V
       5: return

  public final void invoke(ink.ptms.chemdah.taboolib.module.database.ColumnSQL);
    Code:
       0: aload_1
       1: ldc           #42                 // String $this$type
       3: invokestatic  #48                 // Method kotlin1822/jvm/internal/Intrinsics.checkNotNullParameter:(Ljava/lang/Object;Ljava/lang/String;)V
       6: aload_1
       7: iconst_1
       8: anewarray     #50                 // class ink/ptms/chemdah/taboolib/module/database/ColumnOptionSQL
      11: astore_2
      12: aload_2
      13: iconst_0
      14: getstatic     #54                 // Field ink/ptms/chemdah/taboolib/module/database/ColumnOptionSQL.UNIQUE_KEY:Link/ptms/chemdah/taboolib/module/database/ColumnOptionSQL;
      17: aastore
      18: aload_2
      19: invokevirtual #60                 // Method ink/ptms/chemdah/taboolib/module/database/ColumnSQL.options:([Link/ptms/chemdah/taboolib/module/database/ColumnOptionSQL;)V
      22: return

  public java.lang.Object invoke(java.lang.Object);
    Code:
       0: aload_0
       1: aload_1
       2: checkcast     #56                 // class ink/ptms/chemdah/taboolib/module/database/ColumnSQL
       5: invokevirtual #63                 // Method invoke:(Link/ptms/chemdah/taboolib/module/database/ColumnSQL;)V
       8: getstatic     #68                 // Field kotlin1822/Unit.INSTANCE:Lkotlin1822/Unit;
      11: areturn

  static {};
    Code:
       0: new           #2                  // class ink/ptms/chemdah/core/database/DatabaseSQL$tableUser$1$2$1
       3: dup
       4: invokespecial #73                 // Method "<init>":()V
       7: putstatic     #75                 // Field INSTANCE:Link/ptms/chemdah/core/database/DatabaseSQL$tableUser$1$2$1;
      10: return
###### DatabaseSQL$tableUser$1$3
final class ink.ptms.chemdah.core.database.DatabaseSQL$tableUser$1$3 extends kotlin1822.jvm.internal.Lambda implements kotlin1822.jvm.functions.Function1<ink.ptms.chemdah.taboolib.module.database.SQL, kotlin1822.Unit> {
  public static final ink.ptms.chemdah.core.database.DatabaseSQL$tableUser$1$3 INSTANCE;

  ink.ptms.chemdah.core.database.DatabaseSQL$tableUser$1$3();
    Code:
       0: aload_0
       1: iconst_1
       2: invokespecial #37                 // Method kotlin1822/jvm/internal/Lambda."<init>":(I)V
       5: return

  public final void invoke(ink.ptms.chemdah.taboolib.module.database.SQL);
    Code:
       0: aload_1
       1: ldc           #42                 // String $this$add
       3: invokestatic  #48                 // Method kotlin1822/jvm/internal/Intrinsics.checkNotNullParameter:(Ljava/lang/Object;Ljava/lang/String;)V
       6: aload_1
       7: getstatic     #54                 // Field ink/ptms/chemdah/taboolib/module/database/ColumnTypeSQL.VARCHAR:Link/ptms/chemdah/taboolib/module/database/ColumnTypeSQL;
      10: bipush        36
      12: iconst_0
      13: getstatic     #57                 // Field ink/ptms/chemdah/core/database/DatabaseSQL$tableUser$1$3$1.INSTANCE:Link/ptms/chemdah/core/database/DatabaseSQL$tableUser$1$3$1;
      16: checkcast     #7                  // class kotlin1822/jvm/functions/Function1
      19: iconst_4
      20: aconst_null
      21: invokestatic  #63                 // Method ink/ptms/chemdah/taboolib/module/database/SQL.type$default:(Link/ptms/chemdah/taboolib/module/database/SQL;Link/ptms/chemdah/taboolib/module/database/ColumnTypeSQL;IILkotlin1822/jvm/functions/Function1;ILjava/lang/Object;)V
      24: return

  public java.lang.Object invoke(java.lang.Object);
    Code:
       0: aload_0
       1: aload_1
       2: checkcast     #59                 // class ink/ptms/chemdah/taboolib/module/database/SQL
       5: invokevirtual #66                 // Method invoke:(Link/ptms/chemdah/taboolib/module/database/SQL;)V
       8: getstatic     #71                 // Field kotlin1822/Unit.INSTANCE:Lkotlin1822/Unit;
      11: areturn

  static {};
    Code:
       0: new           #2                  // class ink/ptms/chemdah/core/database/DatabaseSQL$tableUser$1$3
       3: dup
       4: invokespecial #76                 // Method "<init>":()V
       7: putstatic     #78                 // Field INSTANCE:Link/ptms/chemdah/core/database/DatabaseSQL$tableUser$1$3;
      10: return
###### DatabaseSQL$tableUser$1$3$1
final class ink.ptms.chemdah.core.database.DatabaseSQL$tableUser$1$3$1 extends kotlin1822.jvm.internal.Lambda implements kotlin1822.jvm.functions.Function1<ink.ptms.chemdah.taboolib.module.database.ColumnSQL, kotlin1822.Unit> {
  public static final ink.ptms.chemdah.core.database.DatabaseSQL$tableUser$1$3$1 INSTANCE;

  ink.ptms.chemdah.core.database.DatabaseSQL$tableUser$1$3$1();
    Code:
       0: aload_0
       1: iconst_1
       2: invokespecial #37                 // Method kotlin1822/jvm/internal/Lambda."<init>":(I)V
       5: return

  public final void invoke(ink.ptms.chemdah.taboolib.module.database.ColumnSQL);
    Code:
       0: aload_1
       1: ldc           #42                 // String $this$type
       3: invokestatic  #48                 // Method kotlin1822/jvm/internal/Intrinsics.checkNotNullParameter:(Ljava/lang/Object;Ljava/lang/String;)V
       6: aload_1
       7: iconst_1
       8: anewarray     #50                 // class ink/ptms/chemdah/taboolib/module/database/ColumnOptionSQL
      11: astore_2
      12: aload_2
      13: iconst_0
      14: getstatic     #54                 // Field ink/ptms/chemdah/taboolib/module/database/ColumnOptionSQL.UNIQUE_KEY:Link/ptms/chemdah/taboolib/module/database/ColumnOptionSQL;
      17: aastore
      18: aload_2
      19: invokevirtual #60                 // Method ink/ptms/chemdah/taboolib/module/database/ColumnSQL.options:([Link/ptms/chemdah/taboolib/module/database/ColumnOptionSQL;)V
      22: return

  public java.lang.Object invoke(java.lang.Object);
    Code:
       0: aload_0
       1: aload_1
       2: checkcast     #56                 // class ink/ptms/chemdah/taboolib/module/database/ColumnSQL
       5: invokevirtual #63                 // Method invoke:(Link/ptms/chemdah/taboolib/module/database/ColumnSQL;)V
       8: getstatic     #68                 // Field kotlin1822/Unit.INSTANCE:Lkotlin1822/Unit;
      11: areturn

  static {};
    Code:
       0: new           #2                  // class ink/ptms/chemdah/core/database/DatabaseSQL$tableUser$1$3$1
       3: dup
       4: invokespecial #73                 // Method "<init>":()V
       7: putstatic     #75                 // Field INSTANCE:Link/ptms/chemdah/core/database/DatabaseSQL$tableUser$1$3$1;
      10: return
###### DatabaseSQL$tableUser$1$4
final class ink.ptms.chemdah.core.database.DatabaseSQL$tableUser$1$4 extends kotlin1822.jvm.internal.Lambda implements kotlin1822.jvm.functions.Function1<ink.ptms.chemdah.taboolib.module.database.SQL, kotlin1822.Unit> {
  public static final ink.ptms.chemdah.core.database.DatabaseSQL$tableUser$1$4 INSTANCE;

  ink.ptms.chemdah.core.database.DatabaseSQL$tableUser$1$4();
    Code:
       0: aload_0
       1: iconst_1
       2: invokespecial #35                 // Method kotlin1822/jvm/internal/Lambda."<init>":(I)V
       5: return

  public final void invoke(ink.ptms.chemdah.taboolib.module.database.SQL);
    Code:
       0: aload_1
       1: ldc           #40                 // String $this$add
       3: invokestatic  #46                 // Method kotlin1822/jvm/internal/Intrinsics.checkNotNullParameter:(Ljava/lang/Object;Ljava/lang/String;)V
       6: aload_1
       7: getstatic     #52                 // Field ink/ptms/chemdah/taboolib/module/database/ColumnTypeSQL.DATE:Link/ptms/chemdah/taboolib/module/database/ColumnTypeSQL;
      10: iconst_0
      11: iconst_0
      12: aconst_null
      13: bipush        14
      15: aconst_null
      16: invokestatic  #58                 // Method ink/ptms/chemdah/taboolib/module/database/SQL.type$default:(Link/ptms/chemdah/taboolib/module/database/SQL;Link/ptms/chemdah/taboolib/module/database/ColumnTypeSQL;IILkotlin1822/jvm/functions/Function1;ILjava/lang/Object;)V
      19: return

  public java.lang.Object invoke(java.lang.Object);
    Code:
       0: aload_0
       1: aload_1
       2: checkcast     #54                 // class ink/ptms/chemdah/taboolib/module/database/SQL
       5: invokevirtual #61                 // Method invoke:(Link/ptms/chemdah/taboolib/module/database/SQL;)V
       8: getstatic     #66                 // Field kotlin1822/Unit.INSTANCE:Lkotlin1822/Unit;
      11: areturn

  static {};
    Code:
       0: new           #2                  // class ink/ptms/chemdah/core/database/DatabaseSQL$tableUser$1$4
       3: dup
       4: invokespecial #71                 // Method "<init>":()V
       7: putstatic     #73                 // Field INSTANCE:Link/ptms/chemdah/core/database/DatabaseSQL$tableUser$1$4;
      10: return
###### DatabaseSQL$tableUserData$1
final class ink.ptms.chemdah.core.database.DatabaseSQL$tableUserData$1 extends kotlin1822.jvm.internal.Lambda implements kotlin1822.jvm.functions.Function1<ink.ptms.chemdah.taboolib.module.database.Table<ink.ptms.chemdah.taboolib.module.database.Host<ink.ptms.chemdah.taboolib.module.database.SQL>, ink.ptms.chemdah.taboolib.module.database.SQL>, kotlin1822.Unit> {
  public static final ink.ptms.chemdah.core.database.DatabaseSQL$tableUserData$1 INSTANCE;

  ink.ptms.chemdah.core.database.DatabaseSQL$tableUserData$1();
    Code:
       0: aload_0
       1: iconst_1
       2: invokespecial #46                 // Method kotlin1822/jvm/internal/Lambda."<init>":(I)V
       5: return

  public final void invoke(ink.ptms.chemdah.taboolib.module.database.Table<ink.ptms.chemdah.taboolib.module.database.Host<ink.ptms.chemdah.taboolib.module.database.SQL>, ink.ptms.chemdah.taboolib.module.database.SQL>);
    Code:
       0: aload_1
       1: ldc           #52                 // String $this$$receiver
       3: invokestatic  #58                 // Method kotlin1822/jvm/internal/Intrinsics.checkNotNullParameter:(Ljava/lang/Object;Ljava/lang/String;)V
       6: aload_1
       7: aconst_null
       8: getstatic     #61                 // Field ink/ptms/chemdah/core/database/DatabaseSQL$tableUserData$1$1.INSTANCE:Link/ptms/chemdah/core/database/DatabaseSQL$tableUserData$1$1;
      11: checkcast     #7                  // class kotlin1822/jvm/functions/Function1
      14: iconst_1
      15: aconst_null
      16: invokestatic  #67                 // Method ink/ptms/chemdah/taboolib/module/database/Table.add$default:(Link/ptms/chemdah/taboolib/module/database/Table;Ljava/lang/String;Lkotlin1822/jvm/functions/Function1;ILjava/lang/Object;)Link/ptms/chemdah/taboolib/module/database/Table;
      19: pop
      20: aload_1
      21: ldc           #69                 // String user
      23: getstatic     #72                 // Field ink/ptms/chemdah/core/database/DatabaseSQL$tableUserData$1$2.INSTANCE:Link/ptms/chemdah/core/database/DatabaseSQL$tableUserData$1$2;
      26: checkcast     #7                  // class kotlin1822/jvm/functions/Function1
      29: invokevirtual #76                 // Method ink/ptms/chemdah/taboolib/module/database/Table.add:(Ljava/lang/String;Lkotlin1822/jvm/functions/Function1;)Link/ptms/chemdah/taboolib/module/database/Table;
      32: pop
      33: aload_1
      34: ldc           #78                 // String key
      36: getstatic     #81                 // Field ink/ptms/chemdah/core/database/DatabaseSQL$tableUserData$1$3.INSTANCE:Link/ptms/chemdah/core/database/DatabaseSQL$tableUserData$1$3;
      39: checkcast     #7                  // class kotlin1822/jvm/functions/Function1
      42: invokevirtual #76                 // Method ink/ptms/chemdah/taboolib/module/database/Table.add:(Ljava/lang/String;Lkotlin1822/jvm/functions/Function1;)Link/ptms/chemdah/taboolib/module/database/Table;
      45: pop
      46: aload_1
      47: ldc           #83                 // String value
      49: getstatic     #86                 // Field ink/ptms/chemdah/core/database/DatabaseSQL$tableUserData$1$4.INSTANCE:Link/ptms/chemdah/core/database/DatabaseSQL$tableUserData$1$4;
      52: checkcast     #7                  // class kotlin1822/jvm/functions/Function1
      55: invokevirtual #76                 // Method ink/ptms/chemdah/taboolib/module/database/Table.add:(Ljava/lang/String;Lkotlin1822/jvm/functions/Function1;)Link/ptms/chemdah/taboolib/module/database/Table;
      58: pop
      59: aload_1
      60: ldc           #88                 // String mode
      62: getstatic     #91                 // Field ink/ptms/chemdah/core/database/DatabaseSQL$tableUserData$1$5.INSTANCE:Link/ptms/chemdah/core/database/DatabaseSQL$tableUserData$1$5;
      65: checkcast     #7                  // class kotlin1822/jvm/functions/Function1
      68: invokevirtual #76                 // Method ink/ptms/chemdah/taboolib/module/database/Table.add:(Ljava/lang/String;Lkotlin1822/jvm/functions/Function1;)Link/ptms/chemdah/taboolib/module/database/Table;
      71: pop
      72: return

  public java.lang.Object invoke(java.lang.Object);
    Code:
       0: aload_0
       1: aload_1
       2: checkcast     #63                 // class ink/ptms/chemdah/taboolib/module/database/Table
       5: invokevirtual #94                 // Method invoke:(Link/ptms/chemdah/taboolib/module/database/Table;)V
       8: getstatic     #99                 // Field kotlin1822/Unit.INSTANCE:Lkotlin1822/Unit;
      11: areturn

  static {};
    Code:
       0: new           #2                  // class ink/ptms/chemdah/core/database/DatabaseSQL$tableUserData$1
       3: dup
       4: invokespecial #103                // Method "<init>":()V
       7: putstatic     #105                // Field INSTANCE:Link/ptms/chemdah/core/database/DatabaseSQL$tableUserData$1;
      10: return
###### DatabaseSQL$tableUserData$1$1
final class ink.ptms.chemdah.core.database.DatabaseSQL$tableUserData$1$1 extends kotlin1822.jvm.internal.Lambda implements kotlin1822.jvm.functions.Function1<ink.ptms.chemdah.taboolib.module.database.SQL, kotlin1822.Unit> {
  public static final ink.ptms.chemdah.core.database.DatabaseSQL$tableUserData$1$1 INSTANCE;

  ink.ptms.chemdah.core.database.DatabaseSQL$tableUserData$1$1();
    Code:
       0: aload_0
       1: iconst_1
       2: invokespecial #35                 // Method kotlin1822/jvm/internal/Lambda."<init>":(I)V
       5: return

  public final void invoke(ink.ptms.chemdah.taboolib.module.database.SQL);
    Code:
       0: aload_1
       1: ldc           #40                 // String $this$add
       3: invokestatic  #46                 // Method kotlin1822/jvm/internal/Intrinsics.checkNotNullParameter:(Ljava/lang/Object;Ljava/lang/String;)V
       6: aload_1
       7: invokevirtual #51                 // Method ink/ptms/chemdah/taboolib/module/database/SQL.id:()V
      10: return

  public java.lang.Object invoke(java.lang.Object);
    Code:
       0: aload_0
       1: aload_1
       2: checkcast     #48                 // class ink/ptms/chemdah/taboolib/module/database/SQL
       5: invokevirtual #54                 // Method invoke:(Link/ptms/chemdah/taboolib/module/database/SQL;)V
       8: getstatic     #59                 // Field kotlin1822/Unit.INSTANCE:Lkotlin1822/Unit;
      11: areturn

  static {};
    Code:
       0: new           #2                  // class ink/ptms/chemdah/core/database/DatabaseSQL$tableUserData$1$1
       3: dup
       4: invokespecial #64                 // Method "<init>":()V
       7: putstatic     #66                 // Field INSTANCE:Link/ptms/chemdah/core/database/DatabaseSQL$tableUserData$1$1;
      10: return
###### DatabaseSQL$tableUserData$1$2
final class ink.ptms.chemdah.core.database.DatabaseSQL$tableUserData$1$2 extends kotlin1822.jvm.internal.Lambda implements kotlin1822.jvm.functions.Function1<ink.ptms.chemdah.taboolib.module.database.SQL, kotlin1822.Unit> {
  public static final ink.ptms.chemdah.core.database.DatabaseSQL$tableUserData$1$2 INSTANCE;

  ink.ptms.chemdah.core.database.DatabaseSQL$tableUserData$1$2();
    Code:
       0: aload_0
       1: iconst_1
       2: invokespecial #37                 // Method kotlin1822/jvm/internal/Lambda."<init>":(I)V
       5: return

  public final void invoke(ink.ptms.chemdah.taboolib.module.database.SQL);
    Code:
       0: aload_1
       1: ldc           #42                 // String $this$add
       3: invokestatic  #48                 // Method kotlin1822/jvm/internal/Intrinsics.checkNotNullParameter:(Ljava/lang/Object;Ljava/lang/String;)V
       6: aload_1
       7: getstatic     #54                 // Field ink/ptms/chemdah/taboolib/module/database/ColumnTypeSQL.INT:Link/ptms/chemdah/taboolib/module/database/ColumnTypeSQL;
      10: bipush        16
      12: iconst_0
      13: getstatic     #57                 // Field ink/ptms/chemdah/core/database/DatabaseSQL$tableUserData$1$2$1.INSTANCE:Link/ptms/chemdah/core/database/DatabaseSQL$tableUserData$1$2$1;
      16: checkcast     #7                  // class kotlin1822/jvm/functions/Function1
      19: iconst_4
      20: aconst_null
      21: invokestatic  #63                 // Method ink/ptms/chemdah/taboolib/module/database/SQL.type$default:(Link/ptms/chemdah/taboolib/module/database/SQL;Link/ptms/chemdah/taboolib/module/database/ColumnTypeSQL;IILkotlin1822/jvm/functions/Function1;ILjava/lang/Object;)V
      24: return

  public java.lang.Object invoke(java.lang.Object);
    Code:
       0: aload_0
       1: aload_1
       2: checkcast     #59                 // class ink/ptms/chemdah/taboolib/module/database/SQL
       5: invokevirtual #66                 // Method invoke:(Link/ptms/chemdah/taboolib/module/database/SQL;)V
       8: getstatic     #71                 // Field kotlin1822/Unit.INSTANCE:Lkotlin1822/Unit;
      11: areturn

  static {};
    Code:
       0: new           #2                  // class ink/ptms/chemdah/core/database/DatabaseSQL$tableUserData$1$2
       3: dup
       4: invokespecial #76                 // Method "<init>":()V
       7: putstatic     #78                 // Field INSTANCE:Link/ptms/chemdah/core/database/DatabaseSQL$tableUserData$1$2;
      10: return
###### DatabaseSQL$tableUserData$1$2$1
final class ink.ptms.chemdah.core.database.DatabaseSQL$tableUserData$1$2$1 extends kotlin1822.jvm.internal.Lambda implements kotlin1822.jvm.functions.Function1<ink.ptms.chemdah.taboolib.module.database.ColumnSQL, kotlin1822.Unit> {
  public static final ink.ptms.chemdah.core.database.DatabaseSQL$tableUserData$1$2$1 INSTANCE;

  ink.ptms.chemdah.core.database.DatabaseSQL$tableUserData$1$2$1();
    Code:
       0: aload_0
       1: iconst_1
       2: invokespecial #37                 // Method kotlin1822/jvm/internal/Lambda."<init>":(I)V
       5: return

  public final void invoke(ink.ptms.chemdah.taboolib.module.database.ColumnSQL);
    Code:
       0: aload_1
       1: ldc           #42                 // String $this$type
       3: invokestatic  #48                 // Method kotlin1822/jvm/internal/Intrinsics.checkNotNullParameter:(Ljava/lang/Object;Ljava/lang/String;)V
       6: aload_1
       7: iconst_1
       8: anewarray     #50                 // class ink/ptms/chemdah/taboolib/module/database/ColumnOptionSQL
      11: astore_2
      12: aload_2
      13: iconst_0
      14: getstatic     #54                 // Field ink/ptms/chemdah/taboolib/module/database/ColumnOptionSQL.KEY:Link/ptms/chemdah/taboolib/module/database/ColumnOptionSQL;
      17: aastore
      18: aload_2
      19: invokevirtual #60                 // Method ink/ptms/chemdah/taboolib/module/database/ColumnSQL.options:([Link/ptms/chemdah/taboolib/module/database/ColumnOptionSQL;)V
      22: return

  public java.lang.Object invoke(java.lang.Object);
    Code:
       0: aload_0
       1: aload_1
       2: checkcast     #56                 // class ink/ptms/chemdah/taboolib/module/database/ColumnSQL
       5: invokevirtual #63                 // Method invoke:(Link/ptms/chemdah/taboolib/module/database/ColumnSQL;)V
       8: getstatic     #68                 // Field kotlin1822/Unit.INSTANCE:Lkotlin1822/Unit;
      11: areturn

  static {};
    Code:
       0: new           #2                  // class ink/ptms/chemdah/core/database/DatabaseSQL$tableUserData$1$2$1
       3: dup
       4: invokespecial #73                 // Method "<init>":()V
       7: putstatic     #75                 // Field INSTANCE:Link/ptms/chemdah/core/database/DatabaseSQL$tableUserData$1$2$1;
      10: return
###### DatabaseSQL$tableUserData$1$3
final class ink.ptms.chemdah.core.database.DatabaseSQL$tableUserData$1$3 extends kotlin1822.jvm.internal.Lambda implements kotlin1822.jvm.functions.Function1<ink.ptms.chemdah.taboolib.module.database.SQL, kotlin1822.Unit> {
  public static final ink.ptms.chemdah.core.database.DatabaseSQL$tableUserData$1$3 INSTANCE;

  ink.ptms.chemdah.core.database.DatabaseSQL$tableUserData$1$3();
    Code:
       0: aload_0
       1: iconst_1
       2: invokespecial #37                 // Method kotlin1822/jvm/internal/Lambda."<init>":(I)V
       5: return

  public final void invoke(ink.ptms.chemdah.taboolib.module.database.SQL);
    Code:
       0: aload_1
       1: ldc           #42                 // String $this$add
       3: invokestatic  #48                 // Method kotlin1822/jvm/internal/Intrinsics.checkNotNullParameter:(Ljava/lang/Object;Ljava/lang/String;)V
       6: aload_1
       7: getstatic     #54                 // Field ink/ptms/chemdah/taboolib/module/database/ColumnTypeSQL.VARCHAR:Link/ptms/chemdah/taboolib/module/database/ColumnTypeSQL;
      10: bipush        64
      12: iconst_0
      13: getstatic     #57                 // Field ink/ptms/chemdah/core/database/DatabaseSQL$tableUserData$1$3$1.INSTANCE:Link/ptms/chemdah/core/database/DatabaseSQL$tableUserData$1$3$1;
      16: checkcast     #7                  // class kotlin1822/jvm/functions/Function1
      19: iconst_4
      20: aconst_null
      21: invokestatic  #63                 // Method ink/ptms/chemdah/taboolib/module/database/SQL.type$default:(Link/ptms/chemdah/taboolib/module/database/SQL;Link/ptms/chemdah/taboolib/module/database/ColumnTypeSQL;IILkotlin1822/jvm/functions/Function1;ILjava/lang/Object;)V
      24: return

  public java.lang.Object invoke(java.lang.Object);
    Code:
       0: aload_0
       1: aload_1
       2: checkcast     #59                 // class ink/ptms/chemdah/taboolib/module/database/SQL
       5: invokevirtual #66                 // Method invoke:(Link/ptms/chemdah/taboolib/module/database/SQL;)V
       8: getstatic     #71                 // Field kotlin1822/Unit.INSTANCE:Lkotlin1822/Unit;
      11: areturn

  static {};
    Code:
       0: new           #2                  // class ink/ptms/chemdah/core/database/DatabaseSQL$tableUserData$1$3
       3: dup
       4: invokespecial #76                 // Method "<init>":()V
       7: putstatic     #78                 // Field INSTANCE:Link/ptms/chemdah/core/database/DatabaseSQL$tableUserData$1$3;
      10: return
###### DatabaseSQL$tableUserData$1$3$1
final class ink.ptms.chemdah.core.database.DatabaseSQL$tableUserData$1$3$1 extends kotlin1822.jvm.internal.Lambda implements kotlin1822.jvm.functions.Function1<ink.ptms.chemdah.taboolib.module.database.ColumnSQL, kotlin1822.Unit> {
  public static final ink.ptms.chemdah.core.database.DatabaseSQL$tableUserData$1$3$1 INSTANCE;

  ink.ptms.chemdah.core.database.DatabaseSQL$tableUserData$1$3$1();
    Code:
       0: aload_0
       1: iconst_1
       2: invokespecial #37                 // Method kotlin1822/jvm/internal/Lambda."<init>":(I)V
       5: return

  public final void invoke(ink.ptms.chemdah.taboolib.module.database.ColumnSQL);
    Code:
       0: aload_1
       1: ldc           #42                 // String $this$type
       3: invokestatic  #48                 // Method kotlin1822/jvm/internal/Intrinsics.checkNotNullParameter:(Ljava/lang/Object;Ljava/lang/String;)V
       6: aload_1
       7: iconst_1
       8: anewarray     #50                 // class ink/ptms/chemdah/taboolib/module/database/ColumnOptionSQL
      11: astore_2
      12: aload_2
      13: iconst_0
      14: getstatic     #54                 // Field ink/ptms/chemdah/taboolib/module/database/ColumnOptionSQL.KEY:Link/ptms/chemdah/taboolib/module/database/ColumnOptionSQL;
      17: aastore
      18: aload_2
      19: invokevirtual #60                 // Method ink/ptms/chemdah/taboolib/module/database/ColumnSQL.options:([Link/ptms/chemdah/taboolib/module/database/ColumnOptionSQL;)V
      22: return

  public java.lang.Object invoke(java.lang.Object);
    Code:
       0: aload_0
       1: aload_1
       2: checkcast     #56                 // class ink/ptms/chemdah/taboolib/module/database/ColumnSQL
       5: invokevirtual #63                 // Method invoke:(Link/ptms/chemdah/taboolib/module/database/ColumnSQL;)V
       8: getstatic     #68                 // Field kotlin1822/Unit.INSTANCE:Lkotlin1822/Unit;
      11: areturn

  static {};
    Code:
       0: new           #2                  // class ink/ptms/chemdah/core/database/DatabaseSQL$tableUserData$1$3$1
       3: dup
       4: invokespecial #73                 // Method "<init>":()V
       7: putstatic     #75                 // Field INSTANCE:Link/ptms/chemdah/core/database/DatabaseSQL$tableUserData$1$3$1;
      10: return
###### DatabaseSQL$tableUserData$1$4
final class ink.ptms.chemdah.core.database.DatabaseSQL$tableUserData$1$4 extends kotlin1822.jvm.internal.Lambda implements kotlin1822.jvm.functions.Function1<ink.ptms.chemdah.taboolib.module.database.SQL, kotlin1822.Unit> {
  public static final ink.ptms.chemdah.core.database.DatabaseSQL$tableUserData$1$4 INSTANCE;

  ink.ptms.chemdah.core.database.DatabaseSQL$tableUserData$1$4();
    Code:
       0: aload_0
       1: iconst_1
       2: invokespecial #35                 // Method kotlin1822/jvm/internal/Lambda."<init>":(I)V
       5: return

  public final void invoke(ink.ptms.chemdah.taboolib.module.database.SQL);
    Code:
       0: aload_1
       1: ldc           #40                 // String $this$add
       3: invokestatic  #46                 // Method kotlin1822/jvm/internal/Intrinsics.checkNotNullParameter:(Ljava/lang/Object;Ljava/lang/String;)V
       6: aload_1
       7: getstatic     #52                 // Field ink/ptms/chemdah/taboolib/module/database/ColumnTypeSQL.VARCHAR:Link/ptms/chemdah/taboolib/module/database/ColumnTypeSQL;
      10: bipush        64
      12: iconst_0
      13: aconst_null
      14: bipush        12
      16: aconst_null
      17: invokestatic  #58                 // Method ink/ptms/chemdah/taboolib/module/database/SQL.type$default:(Link/ptms/chemdah/taboolib/module/database/SQL;Link/ptms/chemdah/taboolib/module/database/ColumnTypeSQL;IILkotlin1822/jvm/functions/Function1;ILjava/lang/Object;)V
      20: return

  public java.lang.Object invoke(java.lang.Object);
    Code:
       0: aload_0
       1: aload_1
       2: checkcast     #54                 // class ink/ptms/chemdah/taboolib/module/database/SQL
       5: invokevirtual #61                 // Method invoke:(Link/ptms/chemdah/taboolib/module/database/SQL;)V
       8: getstatic     #66                 // Field kotlin1822/Unit.INSTANCE:Lkotlin1822/Unit;
      11: areturn

  static {};
    Code:
       0: new           #2                  // class ink/ptms/chemdah/core/database/DatabaseSQL$tableUserData$1$4
       3: dup
       4: invokespecial #71                 // Method "<init>":()V
       7: putstatic     #73                 // Field INSTANCE:Link/ptms/chemdah/core/database/DatabaseSQL$tableUserData$1$4;
      10: return
###### DatabaseSQL$tableUserData$1$5
final class ink.ptms.chemdah.core.database.DatabaseSQL$tableUserData$1$5 extends kotlin1822.jvm.internal.Lambda implements kotlin1822.jvm.functions.Function1<ink.ptms.chemdah.taboolib.module.database.SQL, kotlin1822.Unit> {
  public static final ink.ptms.chemdah.core.database.DatabaseSQL$tableUserData$1$5 INSTANCE;

  ink.ptms.chemdah.core.database.DatabaseSQL$tableUserData$1$5();
    Code:
       0: aload_0
       1: iconst_1
       2: invokespecial #35                 // Method kotlin1822/jvm/internal/Lambda."<init>":(I)V
       5: return

  public final void invoke(ink.ptms.chemdah.taboolib.module.database.SQL);
    Code:
       0: aload_1
       1: ldc           #40                 // String $this$add
       3: invokestatic  #46                 // Method kotlin1822/jvm/internal/Intrinsics.checkNotNullParameter:(Ljava/lang/Object;Ljava/lang/String;)V
       6: aload_1
       7: getstatic     #52                 // Field ink/ptms/chemdah/taboolib/module/database/ColumnTypeSQL.BOOL:Link/ptms/chemdah/taboolib/module/database/ColumnTypeSQL;
      10: iconst_0
      11: iconst_0
      12: aconst_null
      13: bipush        14
      15: aconst_null
      16: invokestatic  #58                 // Method ink/ptms/chemdah/taboolib/module/database/SQL.type$default:(Link/ptms/chemdah/taboolib/module/database/SQL;Link/ptms/chemdah/taboolib/module/database/ColumnTypeSQL;IILkotlin1822/jvm/functions/Function1;ILjava/lang/Object;)V
      19: return

  public java.lang.Object invoke(java.lang.Object);
    Code:
       0: aload_0
       1: aload_1
       2: checkcast     #54                 // class ink/ptms/chemdah/taboolib/module/database/SQL
       5: invokevirtual #61                 // Method invoke:(Link/ptms/chemdah/taboolib/module/database/SQL;)V
       8: getstatic     #66                 // Field kotlin1822/Unit.INSTANCE:Lkotlin1822/Unit;
      11: areturn

  static {};
    Code:
       0: new           #2                  // class ink/ptms/chemdah/core/database/DatabaseSQL$tableUserData$1$5
       3: dup
       4: invokespecial #71                 // Method "<init>":()V
       7: putstatic     #73                 // Field INSTANCE:Link/ptms/chemdah/core/database/DatabaseSQL$tableUserData$1$5;
      10: return
###### DatabaseSQL$tableVariables$1
final class ink.ptms.chemdah.core.database.DatabaseSQL$tableVariables$1 extends kotlin1822.jvm.internal.Lambda implements kotlin1822.jvm.functions.Function1<ink.ptms.chemdah.taboolib.module.database.Table<ink.ptms.chemdah.taboolib.module.database.Host<ink.ptms.chemdah.taboolib.module.database.SQL>, ink.ptms.chemdah.taboolib.module.database.SQL>, kotlin1822.Unit> {
  public static final ink.ptms.chemdah.core.database.DatabaseSQL$tableVariables$1 INSTANCE;

  ink.ptms.chemdah.core.database.DatabaseSQL$tableVariables$1();
    Code:
       0: aload_0
       1: iconst_1
       2: invokespecial #44                 // Method kotlin1822/jvm/internal/Lambda."<init>":(I)V
       5: return

  public final void invoke(ink.ptms.chemdah.taboolib.module.database.Table<ink.ptms.chemdah.taboolib.module.database.Host<ink.ptms.chemdah.taboolib.module.database.SQL>, ink.ptms.chemdah.taboolib.module.database.SQL>);
    Code:
       0: aload_1
       1: ldc           #50                 // String $this$$receiver
       3: invokestatic  #56                 // Method kotlin1822/jvm/internal/Intrinsics.checkNotNullParameter:(Ljava/lang/Object;Ljava/lang/String;)V
       6: aload_1
       7: aconst_null
       8: getstatic     #59                 // Field ink/ptms/chemdah/core/database/DatabaseSQL$tableVariables$1$1.INSTANCE:Link/ptms/chemdah/core/database/DatabaseSQL$tableVariables$1$1;
      11: checkcast     #7                  // class kotlin1822/jvm/functions/Function1
      14: iconst_1
      15: aconst_null
      16: invokestatic  #65                 // Method ink/ptms/chemdah/taboolib/module/database/Table.add$default:(Link/ptms/chemdah/taboolib/module/database/Table;Ljava/lang/String;Lkotlin1822/jvm/functions/Function1;ILjava/lang/Object;)Link/ptms/chemdah/taboolib/module/database/Table;
      19: pop
      20: aload_1
      21: ldc           #67                 // String name
      23: getstatic     #70                 // Field ink/ptms/chemdah/core/database/DatabaseSQL$tableVariables$1$2.INSTANCE:Link/ptms/chemdah/core/database/DatabaseSQL$tableVariables$1$2;
      26: checkcast     #7                  // class kotlin1822/jvm/functions/Function1
      29: invokevirtual #74                 // Method ink/ptms/chemdah/taboolib/module/database/Table.add:(Ljava/lang/String;Lkotlin1822/jvm/functions/Function1;)Link/ptms/chemdah/taboolib/module/database/Table;
      32: pop
      33: aload_1
      34: ldc           #76                 // String data
      36: getstatic     #79                 // Field ink/ptms/chemdah/core/database/DatabaseSQL$tableVariables$1$3.INSTANCE:Link/ptms/chemdah/core/database/DatabaseSQL$tableVariables$1$3;
      39: checkcast     #7                  // class kotlin1822/jvm/functions/Function1
      42: invokevirtual #74                 // Method ink/ptms/chemdah/taboolib/module/database/Table.add:(Ljava/lang/String;Lkotlin1822/jvm/functions/Function1;)Link/ptms/chemdah/taboolib/module/database/Table;
      45: pop
      46: aload_1
      47: ldc           #81                 // String mode
      49: getstatic     #84                 // Field ink/ptms/chemdah/core/database/DatabaseSQL$tableVariables$1$4.INSTANCE:Link/ptms/chemdah/core/database/DatabaseSQL$tableVariables$1$4;
      52: checkcast     #7                  // class kotlin1822/jvm/functions/Function1
      55: invokevirtual #74                 // Method ink/ptms/chemdah/taboolib/module/database/Table.add:(Ljava/lang/String;Lkotlin1822/jvm/functions/Function1;)Link/ptms/chemdah/taboolib/module/database/Table;
      58: pop
      59: return

  public java.lang.Object invoke(java.lang.Object);
    Code:
       0: aload_0
       1: aload_1
       2: checkcast     #61                 // class ink/ptms/chemdah/taboolib/module/database/Table
       5: invokevirtual #87                 // Method invoke:(Link/ptms/chemdah/taboolib/module/database/Table;)V
       8: getstatic     #92                 // Field kotlin1822/Unit.INSTANCE:Lkotlin1822/Unit;
      11: areturn

  static {};
    Code:
       0: new           #2                  // class ink/ptms/chemdah/core/database/DatabaseSQL$tableVariables$1
       3: dup
       4: invokespecial #96                 // Method "<init>":()V
       7: putstatic     #98                 // Field INSTANCE:Link/ptms/chemdah/core/database/DatabaseSQL$tableVariables$1;
      10: return
###### DatabaseSQL$tableVariables$1$1
final class ink.ptms.chemdah.core.database.DatabaseSQL$tableVariables$1$1 extends kotlin1822.jvm.internal.Lambda implements kotlin1822.jvm.functions.Function1<ink.ptms.chemdah.taboolib.module.database.SQL, kotlin1822.Unit> {
  public static final ink.ptms.chemdah.core.database.DatabaseSQL$tableVariables$1$1 INSTANCE;

  ink.ptms.chemdah.core.database.DatabaseSQL$tableVariables$1$1();
    Code:
       0: aload_0
       1: iconst_1
       2: invokespecial #35                 // Method kotlin1822/jvm/internal/Lambda."<init>":(I)V
       5: return

  public final void invoke(ink.ptms.chemdah.taboolib.module.database.SQL);
    Code:
       0: aload_1
       1: ldc           #40                 // String $this$add
       3: invokestatic  #46                 // Method kotlin1822/jvm/internal/Intrinsics.checkNotNullParameter:(Ljava/lang/Object;Ljava/lang/String;)V
       6: aload_1
       7: invokevirtual #51                 // Method ink/ptms/chemdah/taboolib/module/database/SQL.id:()V
      10: return

  public java.lang.Object invoke(java.lang.Object);
    Code:
       0: aload_0
       1: aload_1
       2: checkcast     #48                 // class ink/ptms/chemdah/taboolib/module/database/SQL
       5: invokevirtual #54                 // Method invoke:(Link/ptms/chemdah/taboolib/module/database/SQL;)V
       8: getstatic     #59                 // Field kotlin1822/Unit.INSTANCE:Lkotlin1822/Unit;
      11: areturn

  static {};
    Code:
       0: new           #2                  // class ink/ptms/chemdah/core/database/DatabaseSQL$tableVariables$1$1
       3: dup
       4: invokespecial #64                 // Method "<init>":()V
       7: putstatic     #66                 // Field INSTANCE:Link/ptms/chemdah/core/database/DatabaseSQL$tableVariables$1$1;
      10: return
###### DatabaseSQL$tableVariables$1$2
final class ink.ptms.chemdah.core.database.DatabaseSQL$tableVariables$1$2 extends kotlin1822.jvm.internal.Lambda implements kotlin1822.jvm.functions.Function1<ink.ptms.chemdah.taboolib.module.database.SQL, kotlin1822.Unit> {
  public static final ink.ptms.chemdah.core.database.DatabaseSQL$tableVariables$1$2 INSTANCE;

  ink.ptms.chemdah.core.database.DatabaseSQL$tableVariables$1$2();
    Code:
       0: aload_0
       1: iconst_1
       2: invokespecial #37                 // Method kotlin1822/jvm/internal/Lambda."<init>":(I)V
       5: return

  public final void invoke(ink.ptms.chemdah.taboolib.module.database.SQL);
    Code:
       0: aload_1
       1: ldc           #42                 // String $this$add
       3: invokestatic  #48                 // Method kotlin1822/jvm/internal/Intrinsics.checkNotNullParameter:(Ljava/lang/Object;Ljava/lang/String;)V
       6: aload_1
       7: getstatic     #54                 // Field ink/ptms/chemdah/taboolib/module/database/ColumnTypeSQL.VARCHAR:Link/ptms/chemdah/taboolib/module/database/ColumnTypeSQL;
      10: bipush        64
      12: iconst_0
      13: getstatic     #57                 // Field ink/ptms/chemdah/core/database/DatabaseSQL$tableVariables$1$2$1.INSTANCE:Link/ptms/chemdah/core/database/DatabaseSQL$tableVariables$1$2$1;
      16: checkcast     #7                  // class kotlin1822/jvm/functions/Function1
      19: iconst_4
      20: aconst_null
      21: invokestatic  #63                 // Method ink/ptms/chemdah/taboolib/module/database/SQL.type$default:(Link/ptms/chemdah/taboolib/module/database/SQL;Link/ptms/chemdah/taboolib/module/database/ColumnTypeSQL;IILkotlin1822/jvm/functions/Function1;ILjava/lang/Object;)V
      24: return

  public java.lang.Object invoke(java.lang.Object);
    Code:
       0: aload_0
       1: aload_1
       2: checkcast     #59                 // class ink/ptms/chemdah/taboolib/module/database/SQL
       5: invokevirtual #66                 // Method invoke:(Link/ptms/chemdah/taboolib/module/database/SQL;)V
       8: getstatic     #71                 // Field kotlin1822/Unit.INSTANCE:Lkotlin1822/Unit;
      11: areturn

  static {};
    Code:
       0: new           #2                  // class ink/ptms/chemdah/core/database/DatabaseSQL$tableVariables$1$2
       3: dup
       4: invokespecial #76                 // Method "<init>":()V
       7: putstatic     #78                 // Field INSTANCE:Link/ptms/chemdah/core/database/DatabaseSQL$tableVariables$1$2;
      10: return
###### DatabaseSQL$tableVariables$1$2$1
final class ink.ptms.chemdah.core.database.DatabaseSQL$tableVariables$1$2$1 extends kotlin1822.jvm.internal.Lambda implements kotlin1822.jvm.functions.Function1<ink.ptms.chemdah.taboolib.module.database.ColumnSQL, kotlin1822.Unit> {
  public static final ink.ptms.chemdah.core.database.DatabaseSQL$tableVariables$1$2$1 INSTANCE;

  ink.ptms.chemdah.core.database.DatabaseSQL$tableVariables$1$2$1();
    Code:
       0: aload_0
       1: iconst_1
       2: invokespecial #37                 // Method kotlin1822/jvm/internal/Lambda."<init>":(I)V
       5: return

  public final void invoke(ink.ptms.chemdah.taboolib.module.database.ColumnSQL);
    Code:
       0: aload_1
       1: ldc           #42                 // String $this$type
       3: invokestatic  #48                 // Method kotlin1822/jvm/internal/Intrinsics.checkNotNullParameter:(Ljava/lang/Object;Ljava/lang/String;)V
       6: aload_1
       7: iconst_1
       8: anewarray     #50                 // class ink/ptms/chemdah/taboolib/module/database/ColumnOptionSQL
      11: astore_2
      12: aload_2
      13: iconst_0
      14: getstatic     #54                 // Field ink/ptms/chemdah/taboolib/module/database/ColumnOptionSQL.UNIQUE_KEY:Link/ptms/chemdah/taboolib/module/database/ColumnOptionSQL;
      17: aastore
      18: aload_2
      19: invokevirtual #60                 // Method ink/ptms/chemdah/taboolib/module/database/ColumnSQL.options:([Link/ptms/chemdah/taboolib/module/database/ColumnOptionSQL;)V
      22: return

  public java.lang.Object invoke(java.lang.Object);
    Code:
       0: aload_0
       1: aload_1
       2: checkcast     #56                 // class ink/ptms/chemdah/taboolib/module/database/ColumnSQL
       5: invokevirtual #63                 // Method invoke:(Link/ptms/chemdah/taboolib/module/database/ColumnSQL;)V
       8: getstatic     #68                 // Field kotlin1822/Unit.INSTANCE:Lkotlin1822/Unit;
      11: areturn

  static {};
    Code:
       0: new           #2                  // class ink/ptms/chemdah/core/database/DatabaseSQL$tableVariables$1$2$1
       3: dup
       4: invokespecial #73                 // Method "<init>":()V
       7: putstatic     #75                 // Field INSTANCE:Link/ptms/chemdah/core/database/DatabaseSQL$tableVariables$1$2$1;
      10: return
###### DatabaseSQL$tableVariables$1$3
final class ink.ptms.chemdah.core.database.DatabaseSQL$tableVariables$1$3 extends kotlin1822.jvm.internal.Lambda implements kotlin1822.jvm.functions.Function1<ink.ptms.chemdah.taboolib.module.database.SQL, kotlin1822.Unit> {
  public static final ink.ptms.chemdah.core.database.DatabaseSQL$tableVariables$1$3 INSTANCE;

  ink.ptms.chemdah.core.database.DatabaseSQL$tableVariables$1$3();
    Code:
       0: aload_0
       1: iconst_1
       2: invokespecial #35                 // Method kotlin1822/jvm/internal/Lambda."<init>":(I)V
       5: return

  public final void invoke(ink.ptms.chemdah.taboolib.module.database.SQL);
    Code:
       0: aload_1
       1: ldc           #40                 // String $this$add
       3: invokestatic  #46                 // Method kotlin1822/jvm/internal/Intrinsics.checkNotNullParameter:(Ljava/lang/Object;Ljava/lang/String;)V
       6: aload_1
       7: getstatic     #52                 // Field ink/ptms/chemdah/taboolib/module/database/ColumnTypeSQL.VARCHAR:Link/ptms/chemdah/taboolib/module/database/ColumnTypeSQL;
      10: bipush        64
      12: iconst_0
      13: aconst_null
      14: bipush        12
      16: aconst_null
      17: invokestatic  #58                 // Method ink/ptms/chemdah/taboolib/module/database/SQL.type$default:(Link/ptms/chemdah/taboolib/module/database/SQL;Link/ptms/chemdah/taboolib/module/database/ColumnTypeSQL;IILkotlin1822/jvm/functions/Function1;ILjava/lang/Object;)V
      20: return

  public java.lang.Object invoke(java.lang.Object);
    Code:
       0: aload_0
       1: aload_1
       2: checkcast     #54                 // class ink/ptms/chemdah/taboolib/module/database/SQL
       5: invokevirtual #61                 // Method invoke:(Link/ptms/chemdah/taboolib/module/database/SQL;)V
       8: getstatic     #66                 // Field kotlin1822/Unit.INSTANCE:Lkotlin1822/Unit;
      11: areturn

  static {};
    Code:
       0: new           #2                  // class ink/ptms/chemdah/core/database/DatabaseSQL$tableVariables$1$3
       3: dup
       4: invokespecial #71                 // Method "<init>":()V
       7: putstatic     #73                 // Field INSTANCE:Link/ptms/chemdah/core/database/DatabaseSQL$tableVariables$1$3;
      10: return
###### DatabaseSQL$tableVariables$1$4
final class ink.ptms.chemdah.core.database.DatabaseSQL$tableVariables$1$4 extends kotlin1822.jvm.internal.Lambda implements kotlin1822.jvm.functions.Function1<ink.ptms.chemdah.taboolib.module.database.SQL, kotlin1822.Unit> {
  public static final ink.ptms.chemdah.core.database.DatabaseSQL$tableVariables$1$4 INSTANCE;

  ink.ptms.chemdah.core.database.DatabaseSQL$tableVariables$1$4();
    Code:
       0: aload_0
       1: iconst_1
       2: invokespecial #35                 // Method kotlin1822/jvm/internal/Lambda."<init>":(I)V
       5: return

  public final void invoke(ink.ptms.chemdah.taboolib.module.database.SQL);
    Code:
       0: aload_1
       1: ldc           #40                 // String $this$add
       3: invokestatic  #46                 // Method kotlin1822/jvm/internal/Intrinsics.checkNotNullParameter:(Ljava/lang/Object;Ljava/lang/String;)V
       6: aload_1
       7: getstatic     #52                 // Field ink/ptms/chemdah/taboolib/module/database/ColumnTypeSQL.BOOL:Link/ptms/chemdah/taboolib/module/database/ColumnTypeSQL;
      10: iconst_0
      11: iconst_0
      12: aconst_null
      13: bipush        14
      15: aconst_null
      16: invokestatic  #58                 // Method ink/ptms/chemdah/taboolib/module/database/SQL.type$default:(Link/ptms/chemdah/taboolib/module/database/SQL;Link/ptms/chemdah/taboolib/module/database/ColumnTypeSQL;IILkotlin1822/jvm/functions/Function1;ILjava/lang/Object;)V
      19: return

  public java.lang.Object invoke(java.lang.Object);
    Code:
       0: aload_0
       1: aload_1
       2: checkcast     #54                 // class ink/ptms/chemdah/taboolib/module/database/SQL
       5: invokevirtual #61                 // Method invoke:(Link/ptms/chemdah/taboolib/module/database/SQL;)V
       8: getstatic     #66                 // Field kotlin1822/Unit.INSTANCE:Lkotlin1822/Unit;
      11: areturn

  static {};
    Code:
       0: new           #2                  // class ink/ptms/chemdah/core/database/DatabaseSQL$tableVariables$1$4
       3: dup
       4: invokespecial #71                 // Method "<init>":()V
       7: putstatic     #73                 // Field INSTANCE:Link/ptms/chemdah/core/database/DatabaseSQL$tableVariables$1$4;
      10: return
